{"gao_id": "GAO-03-1172T", "published": "2003-09-23T13:00:00Z", "released": "2003-09-23T09:00:00Z", "summary": "", "title": "VA Benefits: Fundamental Changes to VA's Disability Criteria Need Careful Consideration", "topics": ["Veterans", "Disabilities", "Compensation", "Disability benefits", "Strategic planning", "Physical disabilities", "Veterans disability compensation", "Program evaluation", "Veterans benefits", "Disability programs"], "type": "reports-testimonies", "url": "https://www.gao.gov/products/gao-03-1172t", "versions": [{"title": "Full Report (9 pages)", "url": "https://www.gao.gov/assets/gao-03-1172t.pdf"}, {"title": "Accessible Text", "url": "https://www.gao.gov/assets/a110365.html"}]}