{"gao_id": "NSIAD-00-149", "published": "2000-07-11T13:07:00Z", "released": "2000-07-11T09:07:00Z", "summary": "", "title": "Defense Acquisitions: Comprehensive Strategy Needed to Improve Ship Cruise Missile Defense", "topics": ["Naval warfare", "Military systems analysis", "Weapons systems", "National Defense", "U.S. Navy", "Defense contingency planning", "Naval procurement", "Procurement planning", "Military vessels", "Defense capabilities", "Missiles"], "type": "reports-testimonies", "url": "https://www.gao.gov/products/nsiad-00-149", "versions": [{"title": "Full Report (58 pages)", "url": "https://www.gao.gov/assets/nsiad-00-149.pdf"}]}