{"gao_id": "GAO-07-1197R", "published": "2007-09-11T13:00:00Z", "released": "2007-09-25T09:00:00Z", "summary": "", "title": "Nuclear Security: DOE and NRC Have Different Security Requirements for Protecting Weapons-Grade Material from Terrorist Attacks", "topics": ["Nuclear facility security", "Independent regulatory commissions", "Nuclear power plants", "Homeland Security", "Security threats", "Terrorism", "Nuclear facilities", "Nuclear materials", "Physical security", "Security regulations", "Security standards"], "type": "reports-testimonies", "url": "https://www.gao.gov/products/gao-07-1197r", "versions": [{"title": "Full Report (7 pages)", "url": "https://www.gao.gov/assets/gao-07-1197r.pdf"}, {"title": "Accessible Text", "url": "https://www.gao.gov/assets/a95171.html"}]}