{"gao_id": "GAO-19-547", "published": "2019-07-17T12:00:00Z", "released": "2019-07-17T08:00:00Z", "summary": "Foreign nationals from 82 treaty countries may obtain E-2 nonimmigrant investor status in the United States. E-2 status allows eligible foreign nationals to temporarily stay here to run a business if they make a \u201csubstantial\u201d investment in it and meet other qualifications. Their employees and family members may also obtain E-2 status. The State Department and U.S. Citizenship and Immigration Services told us determining E-2...", "title": "Nonimmigrant Investors: Actions Needed to Improve E-2 Visa Adjudication and Fraud Coordination", "topics": ["Policies and procedures", "Homeland Security", "Immigration fraud", "Immigration services", "Internal controls", "Foreign nationals", "Information sharing", "Documentation", "Visa adjudication", "Dependents", "Eligibility criteria", "Risk management"], "type": "reports-testimonies", "url": "https://www.gao.gov/products/gao-19-547", "versions": [{"title": "Highlights Page (1 page)", "url": "https://www.gao.gov/assets/gao-19-547-highlights.pdf"}, {"title": "Full Report (93 pages)", "url": "https://www.gao.gov/assets/gao-19-547.pdf"}, {"title": "Accessible PDF (113 pages)", "url": "https://www.gao.gov/assets/710/700705.pdf"}]}