{"gao_id": "GAO-24-107051", "published": "2024-03-20T12:00:00Z", "released": "2024-03-20T08:00:00Z", "summary": "U.S. Border Patrol's Missing Migrant Program helps rescue migrants in distress, prevent migrant deaths, and recover human remains along the southwest border. Border Patrol must submit annual reports to Congress on this issue, including data on migrant rescues and deaths. In April 2022 , we found that Border Patrol hadn't collected, recorded, or reported to Congress complete data on migrant deaths. As of March 2024...", "title": "Border Security: Border Patrol's Missing Migrant Program", "topics": ["Border control", "Death data", "Homeland Security", "Performance measurement", "Audit objectives", "Homeland security", "Social media", "Deaths", "Border patrol", "Data collection", "Agency evaluations"], "type": "reports-testimonies", "url": "https://www.gao.gov/products/gao-24-107051", "versions": [{"title": "Full Report (9 pages)", "url": "https://www.gao.gov/assets/d24107051.pdf"}]}