{"gao_id": "GAO-01-69", "published": "2000-10-19T13:10:00Z", "released": "2000-10-19T09:10:00Z", "summary": "", "title": "Internet Pharmacies: Adding Disclosure Requirements Would Aid State and Federal Oversight", "topics": ["Law enforcement", "Health care services", "Consumer protection", "Pharmaceutical industry", "Business Regulation and Consumer Protection", "Internet", "Drugs", "Interstate commerce", "E-commerce", "Websites", "Licenses"], "type": "reports-testimonies", "url": "https://www.gao.gov/products/gao-01-69", "versions": [{"title": "Full Report (62 pages)", "url": "https://www.gao.gov/assets/gao-01-69.pdf"}]}