{"gao_id": "GAO-15-739", "published": "2015-09-04T12:00:00Z", "released": "2015-09-16T08:00:00Z", "summary": "", "title": "Positive Train Control: Additional Oversight Needed As Most Railroads Do Not Expect to Meet 2015 Implementation Deadline", "topics": ["Railroad regulation", "Railroad transportation operations", "Transportation", "Railroad tracks", "Risk management", "Systems design", "Internal controls", "Freight trains", "Railroad industry", "Railroad safety", "Commuter rail"], "type": "reports-testimonies", "url": "https://www.gao.gov/products/gao-15-739", "versions": [{"title": "Highlights Page (1 page)", "url": "https://www.gao.gov/assets/gao-15-739-highlights.pdf"}, {"title": "Full Report (51 pages)", "url": "https://www.gao.gov/assets/gao-15-739.pdf"}, {"title": "Accessible PDF (55 pages)", "url": "https://www.gao.gov/assets/680/672717.pdf"}]}