{"gao_id": "GAO-01-4", "published": "2000-10-27T13:10:00Z", "released": "2000-11-06T08:11:00Z", "summary": "", "title": "Influenza Pandemic: Plan Needed for Federal and State Response", "topics": ["Public health", "Emergency preparedness", "Health care services", "Influenza", "Health statistics", "Epidemics", "Pandemic", "Immunization services", "Health Care", "state relations", "Infectious diseases"], "type": "reports-testimonies", "url": "https://www.gao.gov/products/gao-01-4", "versions": [{"title": "Full Report (40 pages)", "url": "https://www.gao.gov/assets/gao-01-4.pdf"}]}