{"gao_id": "GAO-13-200", "published": "2013-02-14T12:00:00Z", "released": "2013-02-14T07:00:00Z", "summary": "", "title": "Registered Sex Offenders: Sharing More Information Will Enable Federal Agencies to Improve Notifications of Sex Offenders' International Travel", "topics": ["Sexual abuse", "Sex crimes", "Requirements definition", "Justice and Law Enforcement", "Homeland security", "Federal agencies", "Interagency relations", "Terrorism", "Law enforcement", "Crimes", "Risk management", "Criminal investigations"], "type": "reports-testimonies", "url": "https://www.gao.gov/products/gao-13-200", "versions": [{"title": "Highlights Page (1 page)", "url": "https://www.gao.gov/assets/gao-13-200-highlights.pdf"}, {"title": "Full Report (51 pages)", "url": "https://www.gao.gov/assets/gao-13-200.pdf"}, {"title": "Accessible Text", "url": "https://www.gao.gov/assets/660/652212.txt"}]}