{"gao_id": "GAO-21-405", "published": "2021-05-20T12:00:00Z", "released": "2021-05-20T08:00:00Z", "summary": "Over 7,000 pedestrians and cyclists died in crashes with motor vehicles in the U.S. in 2019. Reducing crash risk can involve changing behaviors. Some risks are well understood, like the danger of high driving speeds. Less is known about how other behaviors, like pedestrian distraction, affect crash risk. States can take on projects like media campaigns to encourage safer behavior among drivers, pedestrians, and cyclists...", "title": "Pedestrians and Cyclists: Better Information to States and Enhanced Performance Management Could Help DOT Improve Safety", "topics": ["Transportation safety", "Performance measurement", "Substance abuse", "Transportation", "Public roads or highways", "Safety", "Highway safety", "Motor vehicles", "Pedestrian safety", "Performance management", "Strategic plan"], "type": "reports-testimonies", "url": "https://www.gao.gov/products/gao-21-405", "versions": [{"title": "Highlights Page (1 page)", "url": "https://www.gao.gov/assets/gao-21-405-highlights.pdf"}, {"title": "Full Report (57 pages)", "url": "https://www.gao.gov/assets/gao-21-405.pdf"}, {"title": "Accessible PDF (66 pages)", "url": "https://www.gao.gov/assets/720/714430.pdf"}]}