{"gao_id": "GAO-02-913", "published": "2002-09-12T13:00:00Z", "released": "2002-10-15T09:00:00Z", "summary": "", "title": "Electronic Transfers: Use by Federal Payment Recipients Has Increased but Obstacles to Greater Participation Remain", "topics": ["Bank deposits", "Program beneficiaries", "Participation rates", "Beneficiaries", "Disability insurance", "Financial institutions", "Federal social security programs", "Electronic funds transfer", "Program evaluation", "Supplemental security income", "Government Operations"], "type": "reports-testimonies", "url": "https://www.gao.gov/products/gao-02-913", "versions": [{"title": "Full Report (73 pages)", "url": "https://www.gao.gov/assets/gao-02-913.pdf"}, {"title": "Accessible Text", "url": "https://www.gao.gov/assets/a235548.html"}]}