{"gao_id": "GAO-08-419T", "published": "2008-01-17T13:00:00Z", "released": "2008-01-17T08:00:00Z", "summary": "", "title": "Export Promotion: Export-Import Bank Has Met Target for Small Business Financing Share", "topics": ["Banking law", "Small business assistance", "International Affairs", "Data integrity", "Financial management", "Statutory law", "Bank loans", "Off-budget federal entities", "Internal controls", "Small business", "Reporting requirements", "Statistical data", "Exporting"], "type": "reports-testimonies", "url": "https://www.gao.gov/products/gao-08-419t", "versions": [{"title": "Highlights", "url": "https://www.gao.gov/assets/gao-08-419t-highlights.pdf"}, {"title": "Full Report (17 pages)", "url": "https://www.gao.gov/assets/gao-08-419t.pdf"}, {"title": "Accessible Text", "url": "https://www.gao.gov/assets/a118742.html"}]}