{"gao_id": "GAO-15-597T", "published": "2015-05-13T12:00:00Z", "released": "2015-05-13T08:00:00Z", "summary": "", "title": "Indian Affairs: Further Actions on GAO Recommendations Needed to Address Systemic Management Challenges with Indian Education", "topics": ["Educational facilities", "Education", "Indian lands", "Facility management", "Risk management", "Schools", "Strategic planning", "Native American education", "Monitoring", "Students", "School management and organization", "Federal funds"], "type": "reports-testimonies", "url": "https://www.gao.gov/products/gao-15-597t", "versions": [{"title": "Highlights Page (1 page)", "url": "https://www.gao.gov/assets/gao-15-597t-highlights.pdf"}, {"title": "Full Report (25 pages)", "url": "https://www.gao.gov/assets/gao-15-597t.pdf"}, {"title": "Accessible PDF (25 pages)", "url": "https://www.gao.gov/assets/680/670380.pdf"}]}