{"gao_id": "GAO-05-231", "published": "2005-05-13T13:00:00Z", "released": "2005-06-13T09:00:00Z", "summary": "", "title": "Information Security: Emerging Cybersecurity Issues Threaten Federal Information Systems", "topics": ["Information technology", "Risk assessment", "Cyber security", "Federal agencies", "Internal controls", "Trojan horses", "Information Security", "Computer security", "Computer crimes", "Internet", "Strategic planning", "Identity theft", "Information security", "Spam", "Information security management", "Websites", "Federal computer incident response capability", "Information systems", "Homeland security", "Regulatory agencies", "Reporting requirements", "E-mail"], "type": "reports-testimonies", "url": "https://www.gao.gov/products/gao-05-231", "versions": [{"title": "Highlights", "url": "https://www.gao.gov/assets/gao-05-231-highlights.pdf"}, {"title": "Full Report (79 pages)", "url": "https://www.gao.gov/assets/gao-05-231.pdf"}, {"title": "Accessible Text", "url": "https://www.gao.gov/assets/a157602.html"}]}