{"gao_id": "GAO-15-83", "published": "2014-10-31T12:00:00Z", "released": "2014-10-31T08:00:00Z", "summary": "", "title": "Government Efficiency and Effectiveness: Inconsistent Definitions and Information Limit the Usefulness of Federal Program Inventories", "topics": ["Publishing", "Program management", "Reporting requirements", "Taxpayers", "Regulatory agencies", "Government Operations", "Best practices", "Federal agencies", "Local governments", "Program inventories", "Strategic planning", "Science, Technology, Engineering, and Mathematics programs", "Nuclear proliferation", "Inventories", "Productivity in government", "Decision making", "Tax expenditures"], "type": "reports-testimonies", "url": "https://www.gao.gov/products/gao-15-83", "versions": [{"title": "Highlights Page (2 pages)", "url": "https://www.gao.gov/assets/gao-15-83-highlights.pdf"}, {"title": "Full Report (48 pages)", "url": "https://www.gao.gov/assets/gao-15-83.pdf"}, {"title": "Accessible Text", "url": "https://www.gao.gov/assets/670/666747.txt"}]}