{"gao_id": "GAO-01-898R", "published": "2001-06-26T13:00:00Z", "released": "2001-06-26T09:00:00Z", "summary": "", "title": "Federally Chartered Corporation: Review of the Financial Statement Audit Report for the National Conference of State Societies, Washington, District of Columbia, for Fiscal Years 1999 and 1998", "topics": ["Federal corporations", "Accounting standards", "Auditing and Financial Management", "Reporting requirements", "Financial statement audits", "Financial audit", "Audit reports", "Cash basis accounting", "Financial statements", "Financial management", "Federally chartered corporation"], "type": "reports-testimonies", "url": "https://www.gao.gov/products/gao-01-898r", "versions": [{"title": "Full Report (2 pages)", "url": "https://www.gao.gov/assets/gao-01-898r.pdf"}]}