{"gao_id": "GAO-04-886T", "published": "2004-07-08T13:00:00Z", "released": "2004-07-08T09:00:00Z", "summary": "", "title": "Fiscal Year 2003 U.S. Government Financial Statements: Sustained Improvement in Federal Financial Management Is Crucial to Addressing Our Nation's Future Fiscal Challenges", "topics": ["Financial records", "Performance measures", "Accounting standards", "Auditing and Financial Management", "Accounting procedures", "Financial statement audits", "Internal controls", "Audit reports", "Reporting requirements", "Accountability", "Financial management systems", "Financial management", "Financial statements", "Federal agency accounting systems"], "type": "reports-testimonies", "url": "https://www.gao.gov/products/gao-04-886t", "versions": [{"title": "Highlights", "url": "https://www.gao.gov/assets/gao-04-886t-highlights.pdf"}, {"title": "Full Report (39 pages)", "url": "https://www.gao.gov/assets/gao-04-886t.pdf"}, {"title": "Accessible Text", "url": "https://www.gao.gov/assets/a111111.html"}]}