{"gao_id": "GAO-09-10", "published": "2008-10-16T13:10:00Z", "released": "2008-11-17T08:11:00Z", "summary": "", "title": "Federal Real Property: Government's Fiscal Exposure from Repair and Maintenance Backlogs Is Unclear", "topics": ["Risk assessment", "Federal property", "Standards", "Reporting requirements", "Federal facilities", "Government Operations", "Construction costs", "Federal agencies", "Maintenance (upkeep)", "Facility maintenance", "Cost analysis", "Federal property management", "Real property", "Schedule slippages", "Risk management", "Assets", "Cost estimates", "Facility repairs", "Maintenance standards", "Agency missions", "Government facility construction", "Maintenance costs", "Federal procurement"], "type": "reports-testimonies", "url": "https://www.gao.gov/products/gao-09-10", "versions": [{"title": "Highlights", "url": "https://www.gao.gov/assets/gao-09-10-highlights.pdf"}, {"title": "Full Report (36 pages)", "url": "https://www.gao.gov/assets/gao-09-10.pdf"}, {"title": "Accessible Text", "url": "https://www.gao.gov/assets/a282806.html"}]}