{"gao_id": "GAO-04-310G", "published": "2004-07-16T12:00:00Z", "released": "2004-07-16T08:00:00Z", "summary": "", "title": "GAO's Congressional Protocols (Superseded by GAO-17-767G)", "topics": ["Standards evaluation", "Congressional protocols", "Agency missions", "Criminal investigations", "Performance measures", "GAO Mission and Operations", "Standards", "Reporting requirements", "Policies and procedures", "Accountability", "Congressional investigations"], "type": "reports-testimonies", "url": "https://www.gao.gov/products/gao-04-310g", "versions": [{"title": "Full Report (27 pages)", "url": "https://www.gao.gov/assets/gao-04-310g.pdf"}, {"title": "Accessible Text", "url": "https://www.gao.gov/assets/a76829.html"}]}