{"gao_id": "RCED-00-57", "published": "2000-02-18T13:00:00Z", "released": "2000-02-23T08:00:00Z", "summary": "", "title": "Aviation and the Environment: Aviation's Effects on the Global Atmosphere Are Potentially Significant and Expected to Grow", "topics": ["Environmental policies", "Global warming", "Aviation", "Thermal pollution", "Aircraft", "Natural Resources and Environment", "Carbon dioxide", "Climate change", "Aviation fuels", "Climate statistics", "Atmospheric research", "Air pollution control", "Hazardous substances", "Pollution monitoring"], "type": "reports-testimonies", "url": "https://www.gao.gov/products/rced-00-57", "versions": [{"title": "Full Report (54 pages)", "url": "https://www.gao.gov/assets/rced-00-57.pdf"}]}