{"gao_id": "GAO-22-104737", "published": "2022-06-16T12:00:00Z", "released": "2022-07-14T08:00:00Z", "summary": "Schools remain divided along racial, ethnic, and economic lines throughout the U.S.\u2014even as the K-12 public school student population grows more diverse. During the 2020-21 school year, more than a third of students (about 18.5 million) attended schools where 75% or more students were of a single race or ethnicity. Because district boundaries often determine which school a student can attend, school district boundaries can...", "title": "K-12 Education: Student Population Has Significantly Diversified, but Many Schools Remain Divided Along Racial, Ethnic, and Economic Lines", "topics": ["School districts", "Racial and ethnic groups", "Hispanic Americans", "Public schools", "Students", "Teachers", "Schools", "Magnet schools", "Charter schools", "Education", "Census"], "type": "reports-testimonies", "url": "https://www.gao.gov/products/gao-22-104737", "versions": [{"title": "Highlights Page (1 page)", "url": "https://www.gao.gov/assets/gao-22-104737-highlights.pdf"}, {"title": "Full Report (45 pages)", "url": "https://www.gao.gov/assets/gao-22-104737.pdf"}, {"title": "Accessible PDF (61 pages)", "url": "https://www.gao.gov/assets/730/721613.pdf"}]}