{"gao_id": "GAO-06-208T", "published": "2005-10-26T13:00:00Z", "released": "2005-10-26T09:00:00Z", "summary": "", "title": "Tax Gap: Multiple Strategies, Better Compliance Data, and Long-Term Goals Are Needed to Improve Taxpayer Compliance", "topics": ["Tax evasion", "Tax violations", "Noncompliance", "Taxpayers", "Strategic planning", "Tax Policy and Administration", "Tax nonpayment", "Econometric modeling", "Tax administration", "Deficit reduction", "Income taxes"], "type": "reports-testimonies", "url": "https://www.gao.gov/products/gao-06-208t", "versions": [{"title": "Highlights", "url": "https://www.gao.gov/assets/gao-06-208t-highlights.pdf"}, {"title": "Full Report (19 pages)", "url": "https://www.gao.gov/assets/gao-06-208t.pdf"}, {"title": "Accessible Text", "url": "https://www.gao.gov/assets/a112460.html"}]}