{"gao_id": "GAO-20-180", "published": "2020-01-16T12:00:00Z", "released": "2020-01-16T07:00:00Z", "summary": "The contractors who run the National Nuclear Security Administration\u2019s 8 sites\u2014including its weapons plants and labs\u2014track and report costs in different ways. However, Congress needs comparable cost information to provide oversight and to make budget decisions across these sites. NNSA is continuing to make progress on implementing a common financial reporting system for its contractors. We found NNSA could do more to ensure that the...", "title": "National Nuclear Security Administration: Additional Verification Checks Could Improve the Accuracy and Consistency of Reported Financial Data", "topics": ["Federal contractors", "National security", "Defense budgets", "Government contracts", "Energy", "Federal spending", "Accounting standards", "Nuclear security", "Overhead costs", "Financial reporting", "Financial integration"], "type": "reports-testimonies", "url": "https://www.gao.gov/products/gao-20-180", "versions": [{"title": "Highlights Page (1 page)", "url": "https://www.gao.gov/assets/gao-20-180-highlights.pdf"}, {"title": "Full Report (47 pages)", "url": "https://www.gao.gov/assets/gao-20-180.pdf"}]}