{"gao_id": "GAO-13-728T", "published": "2013-06-20T12:00:00Z", "released": "2013-06-20T08:00:00Z", "summary": "", "title": "Personnel Security Clearances: Further Actions Needed to Improve the Process and Realize Efficiencies", "topics": ["Civil procedure", "Government Operations", "Employees", "Security clearances", "Executive orders", "Eligibility determinations", "Federal intelligence agencies", "Investigations by federal agencies", "Classified information", "Investigations into federal agencies", "Reporting requirements", "Background investigations", "Executive agencies", "Information classification", "Documentation", "Classified defense information", "Homeland security", "Defense capabilities", "Civilian employees", "Decision making"], "type": "reports-testimonies", "url": "https://www.gao.gov/products/gao-13-728t", "versions": [{"title": "Highlights Page (1 page)", "url": "https://www.gao.gov/assets/gao-13-728t-highlights.pdf"}, {"title": "Full Report (17 pages)", "url": "https://www.gao.gov/assets/gao-13-728t.pdf"}, {"title": "Accessible Text", "url": "https://www.gao.gov/assets/660/655385.txt"}]}