{"gao_id": "GAO-18-487", "published": "2018-06-27T12:00:00Z", "released": "2018-06-27T08:00:00Z", "summary": "", "title": "U.S. Customs and Border Protection: Progress and Challenges in Recruiting, Hiring, and Retaining Law Enforcement Personnel", "topics": ["Justice and Law Enforcement", "Human capital management", "Border patrol officers", "Pay rates", "Retention incentives", "Employee retention", "Financial incentives", "Staffing levels", "Border patrol", "Law enforcement", "Background investigations", "Law enforcement personnel", "Personnel recruiting", "Attrition rates", "Polygraph"], "type": "reports-testimonies", "url": "https://www.gao.gov/products/gao-18-487", "versions": [{"title": "Highlights Page (1 page)", "url": "https://www.gao.gov/assets/gao-18-487-highlights.pdf"}, {"title": "Full Report (72 pages)", "url": "https://www.gao.gov/assets/gao-18-487.pdf"}, {"title": "Accessible PDF (86 pages)", "url": "https://www.gao.gov/assets/700/693407.pdf"}]}