{"gao_id": "GAO-06-80", "published": "2005-12-05T13:00:00Z", "released": "2005-12-05T08:00:00Z", "summary": "", "title": "Older Workers: Labor Can Help Employers and Employees Plan Better for the Future", "topics": ["Labor force", "Older workers", "Retirement", "Occupational surveys", "Baby boomers", "Personnel recruiting", "Hiring policies", "Pensions", "Retirement benefits", "Employee retention", "Retirement Security"], "type": "reports-testimonies", "url": "https://www.gao.gov/products/gao-06-80", "versions": [{"title": "Highlights", "url": "https://www.gao.gov/assets/gao-06-80-highlights.pdf"}, {"title": "Full Report (60 pages)", "url": "https://www.gao.gov/assets/gao-06-80.pdf"}, {"title": "Accessible Text", "url": "https://www.gao.gov/assets/a248676.html"}]}