{"gao_id": "GAO-07-457", "published": "2007-04-06T13:00:00Z", "released": "2007-04-19T09:00:00Z", "summary": "", "title": "International Organizations: Assistance Programs Constrained in Burma", "topics": ["Prisoners", "International relations", "International cooperation", "Refugees", "Foreign governments", "Foreign aid programs", "Program evaluation", "AIDS", "Military government", "Military regimes", "International Affairs", "International food programs", "International organizations"], "type": "reports-testimonies", "url": "https://www.gao.gov/products/gao-07-457", "versions": [{"title": "Highlights", "url": "https://www.gao.gov/assets/gao-07-457-highlights.pdf"}, {"title": "Full Report (46 pages)", "url": "https://www.gao.gov/assets/gao-07-457.pdf"}, {"title": "Accessible Text", "url": "https://www.gao.gov/assets/a259032.html"}]}