{"gao_id": "GAO-21-461T", "published": "2021-03-17T12:00:00Z", "released": "2021-03-17T08:00:00Z", "summary": "Critical skill gaps are making it difficult for federal agencies to carry out their missions\u2014particularly in science and technology. Our past work and recommendations outlined 3 key areas for building the federal science and technology workforce: strategic planning to identify skill gaps and future needs; improving federal pay and hiring; and addressing factors affecting the work environment, like sexual harassment. We testified that while agencies...", "title": "Science and Technology: Strengthening and Sustaining the Federal Science and Technology Workforce", "topics": ["Science and technology", "Workforce planning", "Federal agencies", "Scientific integrity", "Human Capital", "Agency evaluations", "Government employees", "Work environment", "Compliance oversight", "Sexual harassment", "Federal hiring", "Federal workforce", "Scientists", "Human capital management"], "type": "reports-testimonies", "url": "https://www.gao.gov/products/gao-21-461t", "versions": [{"title": "Highlights Page (1 page)", "url": "https://www.gao.gov/assets/gao-21-461t-highlights.pdf"}, {"title": "Full Report (21 pages)", "url": "https://www.gao.gov/assets/gao-21-461t.pdf"}, {"title": "Accessible PDF (23 pages)", "url": "https://www.gao.gov/assets/720/713079.pdf"}]}