{"gao_id": "GAO-16-27", "published": "2015-11-16T12:00:00Z", "released": "2015-11-16T07:00:00Z", "summary": "", "title": "Small Business: Action Needed to Determine Whether DOD's Comprehensive Subcontracting Plan Test Program Should Be Made Permanent", "topics": ["Subcontracting", "Cost savings", "Program evaluation", "Procurement planning", "Prime contractors", "Small business", "Business Regulation and Consumer Protection", "Administrative costs", "Research programs", "Department of Defense contractors"], "type": "reports-testimonies", "url": "https://www.gao.gov/products/gao-16-27", "versions": [{"title": "Highlights Page (1 page)", "url": "https://www.gao.gov/assets/gao-16-27-highlights.pdf"}, {"title": "Full Report (36 pages)", "url": "https://www.gao.gov/assets/gao-16-27.pdf"}, {"title": "Accessible PDF (41 pages)", "url": "https://www.gao.gov/assets/690/681832.pdf"}]}