{"gao_id": "GAO-06-178", "published": "2006-02-01T13:00:00Z", "released": "2006-03-03T08:00:00Z", "summary": "", "title": "Electronic Government: Agencies Face Challenges in Implementing New Federal Employee Identification Standard", "topics": ["Smart cards", "Identification cards", "Federal agencies", "Personal identity verification", "Authorization", "Federal Information Processing Standards", "Interoperability", "Program evaluation", "Facility security", "Government Operations", "Identity verification"], "type": "reports-testimonies", "url": "https://www.gao.gov/products/gao-06-178", "versions": [{"title": "Highlights", "url": "https://www.gao.gov/assets/gao-06-178-highlights.pdf"}, {"title": "Full Report (60 pages)", "url": "https://www.gao.gov/assets/gao-06-178.pdf"}, {"title": "Accessible Text", "url": "https://www.gao.gov/assets/a249007.html"}]}