{"gao_id": "GAO-01-811", "published": "2001-09-25T13:00:00Z", "released": "2001-10-12T09:00:00Z", "summary": "", "title": "Intellectual Property: State Immunity in Infringement Actions", "topics": ["Patents", "Federal case law", "Copyright", "Constitutional law", "Justice and Law Enforcement", "Trademarks", "Intellectual property rights", "Intellectual property", "Litigation", "Federal courts", "Property rights"], "type": "reports-testimonies", "url": "https://www.gao.gov/products/gao-01-811", "versions": [{"title": "Full Report (78 pages)", "url": "https://www.gao.gov/assets/gao-01-811.pdf"}]}