{"gao_id": "GAO-08-940", "published": "2008-09-25T13:09:00Z", "released": "2008-09-25T09:09:00Z", "summary": "", "title": "U.S. Asylum System: Significant Variation Existed in Asylum Outcomes across Immigration Courts and Judges", "topics": ["Judicial remedies", "Immigration status", "Judicial review", "Immigration enforcement", "Judicial opinions", "Data integrity", "Data collection", "Statistical data", "Appeals", "Immigration", "Judges", "Legal opinions", "Performance measures", "Courtroom proceedings", "Political refugees", "Immigrants", "Litigation", "Claims processing", "Asylum", "Justice and Law Enforcement", "Immigration and naturalization law", "Policies and procedures"], "type": "reports-testimonies", "url": "https://www.gao.gov/products/gao-08-940", "versions": [{"title": "Highlights", "url": "https://www.gao.gov/assets/gao-08-940-highlights.pdf"}, {"title": "Full Report (137 pages)", "url": "https://www.gao.gov/assets/gao-08-940.pdf"}, {"title": "Accessible Text", "url": "https://www.gao.gov/assets/a281805.html"}]}