{"gao_id": "GAO-22-105056", "published": "2022-02-03T12:00:00Z", "released": "2022-02-03T07:00:00Z", "summary": "Globally, millions of people work under threat or coercion. DOD has policies to prevent the sale of goods produced by forced labor at the nearly 3,000 military commissaries and exchanges it operates worldwide. But the commissaries and exchanges implement DOD's policies differently. DOD needs a consistent approach to reasonably assure goods produced by forced labor aren't being sold. Further, DOD doesn't monitor compliance with its...", "title": "Forced Labor: Actions Needed to Better Prevent the Availability of At-Risk Goods in DOD's Commissaries and Exchanges", "topics": ["Child labor", "Compliance oversight", "Military commissaries", "Human trafficking", "Imports", "Post exchanges", "Best practices", "Commodities exchanges", "Forced labor", "National Defense", "Military forces"], "type": "reports-testimonies", "url": "https://www.gao.gov/products/gao-22-105056", "versions": [{"title": "Highlights Page (1 page)", "url": "https://www.gao.gov/assets/gao-22-105056-highlights.pdf"}, {"title": "Full Report (58 pages)", "url": "https://www.gao.gov/assets/gao-22-105056.pdf"}, {"title": "Accessible PDF (65 pages)", "url": "https://www.gao.gov/assets/720/718890.pdf"}]}