{"gao_id": "GAO-13-123", "published": "2013-08-02T12:00:00Z", "released": "2013-09-03T08:00:00Z", "summary": "", "title": "DOD Financial Management: Ineffective Risk Management Could Impair Progress toward Audit-Ready Financial Statements", "topics": ["Strategic planning", "Budget functions", "Monitoring", "Defense procurement", "Internal controls", "Internal audits", "Military forces", "Auditing standards", "Accounting", "Reporting requirements", "Financial management systems", "Financial management", "Risk management", "Risk assessment", "Accountability", "Documentation", "National Defense", "Policy evaluation", "Financial statement audits"], "type": "reports-testimonies", "url": "https://www.gao.gov/products/gao-13-123", "versions": [{"title": "Highlights Page (1 page)", "url": "https://www.gao.gov/assets/gao-13-123-highlights.pdf"}, {"title": "Full Report (47 pages)", "url": "https://www.gao.gov/assets/gao-13-123.pdf"}, {"title": "Accessible Text", "url": "https://www.gao.gov/assets/660/657385.txt"}]}