{"gao_id": "GAO-04-154", "published": "2004-01-30T13:00:00Z", "released": "2004-03-01T08:00:00Z", "summary": "", "title": "Information Security: Further Efforts Needed to Address Serious Weaknesses to USDA", "topics": ["Information security", "Computer security", "Agency missions", "Strategic planning", "Access control", "Internal controls", "Computer networks", "Information resources management", "System software", "Automated security systems", "Information Security", "Information systems"], "type": "reports-testimonies", "url": "https://www.gao.gov/products/gao-04-154", "versions": [{"title": "Highlights", "url": "https://www.gao.gov/assets/gao-04-154-highlights.pdf"}, {"title": "Full Report (34 pages)", "url": "https://www.gao.gov/assets/gao-04-154.pdf"}, {"title": "Accessible Text", "url": "https://www.gao.gov/assets/a241231.html"}]}