{"gao_id": "GAO-19-77", "published": "2018-12-04T12:00:00Z", "released": "2018-12-04T07:00:00Z", "summary": "Human trafficking victims are often held in slave-like conditions and forced to work in areas such as the commercial sex trade, factories, and agriculture. The Departments of State and Labor, and the U.S. Agency for International Development managed 120 counter-trafficking projects in FY 2017. These projects were carried out by grantees and others, and overseen by the agencies. We found some weaknesses in State\u2019s and...", "title": "Human Trafficking: State and USAID Should Improve Their Monitoring of International Counter-trafficking Projects", "topics": ["Forced labor", "Performance monitoring", "Child labor", "International Affairs", "Crimes", "Human trafficking", "Documentation", "Human rights", "Agency evaluations", "Children", "Data collection", "Performance measurement", "Internal controls"], "type": "reports-testimonies", "url": "https://www.gao.gov/products/gao-19-77", "versions": [{"title": "Highlights Page (1 page)", "url": "https://www.gao.gov/assets/gao-19-77-highlights.pdf"}, {"title": "Full Report (84 pages)", "url": "https://www.gao.gov/assets/gao-19-77.pdf"}, {"title": "Accessible PDF (94 pages)", "url": "https://www.gao.gov/assets/700/695862.pdf"}]}