{"gao_id": "GAO-14-640", "published": "2014-09-08T12:00:00Z", "released": "2014-09-08T08:00:00Z", "summary": "", "title": "Personnel Security Clearances: Additional Guidance and Oversight Needed at DHS and DOD to Ensure Consistent Application of Revocation Process", "topics": ["Government employees", "Homeland Security", "Classified information", "Access control", "Policies and procedures", "Personnel security clearances", "Homeland security", "Eligibility determinations", "Executive orders", "Information access", "Federal employees"], "type": "reports-testimonies", "url": "https://www.gao.gov/products/gao-14-640", "versions": [{"title": "Highlights Page (1 page)", "url": "https://www.gao.gov/assets/gao-14-640-highlights.pdf"}, {"title": "Full Report (89 pages)", "url": "https://www.gao.gov/assets/gao-14-640.pdf"}, {"title": "Accessible Text", "url": "https://www.gao.gov/assets/670/665610.txt"}]}