{"gao_id": "GAO-01-699T", "published": "2001-05-10T13:00:00Z", "released": "2001-05-10T09:00:00Z", "summary": "", "title": "Commercial Fisheries: Effectiveness of Fishing Buyback Programs Can Be Improved", "topics": ["Natural Resources and Environment", "Fishing industry", "Fishery", "Marine resources conservation", "Fishery legislation", "Fish", "Salmon", "Natural resources", "Sustainable fisheries", "Program evaluation", "Licenses"], "type": "reports-testimonies", "url": "https://www.gao.gov/products/gao-01-699t", "versions": [{"title": "Full Report (8 pages)", "url": "https://www.gao.gov/assets/gao-01-699t.pdf"}]}