{"gao_id": "GAO-12-618", "published": "2012-05-31T12:00:00Z", "released": "2012-05-31T08:00:00Z", "summary": "", "title": "Inspectors General: HUD Office of Inspector General Resources and Results", "topics": ["Housing programs", "Audits", "Prison costs", "Disaster assistance", "Urban development", "Convictions", "Communities", "Budgets", "Economic stimulus", "Housing"], "type": "reports-testimonies", "url": "https://www.gao.gov/products/gao-12-618", "versions": [{"title": "Highlights Page (1 page)", "url": "https://www.gao.gov/assets/gao-12-618-highlights.pdf"}, {"title": "Full Report (26 pages)", "url": "https://www.gao.gov/assets/gao-12-618.pdf"}, {"title": "Accessible Text", "url": "https://www.gao.gov/assets/600/591277.txt"}]}