{"gao_id": "AIMD-00-259", "published": "2000-09-15T13:09:00Z", "released": "2000-09-15T09:09:00Z", "summary": "", "title": "Indian Trust Funds: Improvements Made in Acquisition of New Asset and Accounting System But Significant Risks Remain", "topics": ["Funds management", "Indian lands", "IT acquisitions", "Trust funds", "Native Americans", "Natural Resources and Environment", "Federal agency accounting systems", "Management reengineering", "Internal controls", "Systems design", "Information resources management"], "type": "reports-testimonies", "url": "https://www.gao.gov/products/aimd-00-259", "versions": [{"title": "Full Report (29 pages)", "url": "https://www.gao.gov/assets/aimd-00-259.pdf"}]}