{"gao_id": "GAO-12-686", "published": "2012-08-10T00:08:00Z", "released": "2012-09-09T20:09:00Z", "summary": "", "title": "Federal Communications Commission: Regulatory Fee Process Needs to Be Updated", "topics": ["Fees", "Television", "Telecommunications industry", "Regulatory agencies", "Broadcasting", "Telecommunications", "Wireline", "Radio", "User fees", "Wireless", "Government Operations"], "type": "reports-testimonies", "url": "https://www.gao.gov/products/gao-12-686", "versions": [{"title": "Highlights Page (1 page)", "url": "https://www.gao.gov/assets/gao-12-686-highlights.pdf"}, {"title": "Full Report (51 pages)", "url": "https://www.gao.gov/assets/gao-12-686.pdf"}, {"title": "Accessible Text", "url": "https://www.gao.gov/assets/650/647861.txt"}]}