{"gao_id": "GAO-04-817T", "published": "2004-06-03T13:00:00Z", "released": "2004-06-03T09:00:00Z", "summary": "", "title": "FBI Transformation: Human Capital Strategies May Assist the FBI in Its Commitment to Address Its Top Priorities", "topics": ["Federal agency reorganization", "Personnel management", "Federal intelligence agencies", "Homeland security", "Staff utilization", "Knowledge, skills and abilities", "Domestic intelligence", "Justice and Law Enforcement", "Human capital", "Strategic planning", "Personnel recruiting", "Employee retention", "Counterterrorism"], "type": "reports-testimonies", "url": "https://www.gao.gov/products/gao-04-817t", "versions": [{"title": "Highlights", "url": "https://www.gao.gov/assets/gao-04-817t-highlights.pdf"}, {"title": "Full Report (16 pages)", "url": "https://www.gao.gov/assets/gao-04-817t.pdf"}, {"title": "Accessible Text", "url": "https://www.gao.gov/assets/a111002.html"}]}