{"gao_id": "GAO-24-106499", "published": "2024-09-16T12:00:00Z", "released": "2024-09-16T08:00:00Z", "summary": "The Department of Defense requested over $15 billion for its military construction program in FY 2025. Projects include child development centers, hangars, and more. Over the last 5 years, poor initial planning contributed to about 25% of the projects being delayed for at least a year. Our recommendations are to help DOD address this issue and others we found in our review. For example, if...", "title": "Military Construction: Better Information Sharing Would Improve DOD's Oversight", "topics": ["Engineering", "Floods", "Military forces", "National Defense", "Defense budgets", "Military construction", "Construction", "Lessons learned", "Industry standards", "Engineers", "Compliance oversight"], "type": "reports-testimonies", "url": "https://www.gao.gov/products/gao-24-106499", "versions": [{"title": "Highlights Page (1 page)", "url": "https://www.gao.gov/assets/gao-24-106499-highlights.pdf"}, {"title": "Full Report (58 pages)", "url": "https://www.gao.gov/assets/gao-24-106499.pdf"}]}