{"gao_id": "GAO-20-182", "published": "2019-12-17T12:00:00Z", "released": "2019-12-17T07:00:00Z", "summary": "Since 1789, the U.S. government\u2019s drawback program has encouraged manufacturing and exports by refunding certain customs duties. For example, a merchant who paid duties on imported fabric, made it into clothes, and then exported the clothes could claim a refund for import duties paid. The program refunds about $1 billion a year. We found problems in how CBP checks these claims. For example, CBP\u2019s new...", "title": "Customs and Border Protection: Risk Management for Tariff Refunds Should Be Improved", "topics": ["Exports", "Tariffs", "Homeland Security", "Border control", "Improper payments", "Risk management", "Manufacturing", "Electronic filing", "Trade facilitation", "Economic analysis", "Industry representatives"], "type": "reports-testimonies", "url": "https://www.gao.gov/products/gao-20-182", "versions": [{"title": "Highlights Page (1 page)", "url": "https://www.gao.gov/assets/gao-20-182-highlights.pdf"}, {"title": "Full Report (65 pages)", "url": "https://www.gao.gov/assets/gao-20-182.pdf"}, {"title": "Accessible PDF (71 pages)", "url": "https://www.gao.gov/assets/710/706683.pdf"}]}