{"gao_id": "GAO-12-514R", "published": "2012-04-25T12:00:00Z", "released": "2012-04-25T08:00:00Z", "summary": "", "title": "Patent and Trademark Office: New User Fee Design Presents Opportunities to Build on Transparency and Communication Success", "topics": ["Audits", "Program transparency", "Corporate stakeholders", "Federal user fees", "Patent applications", "Appropriations", "Federal rulemaking", "User fees", "Intellectual property", "Government Operations", "Protocols"], "type": "reports-testimonies", "url": "https://www.gao.gov/products/gao-12-514r", "versions": [{"title": "Full Report (36 pages)", "url": "https://www.gao.gov/assets/gao-12-514r.pdf"}, {"title": "Accessible Text", "url": "https://www.gao.gov/assets/600/590397.txt"}]}