{"gao_id": "GAO-02-394", "published": "2002-04-25T13:00:00Z", "released": "2002-04-25T09:00:00Z", "summary": "", "title": "Special Education: Grant Programs Designed to Serve Children Ages 0-5", "topics": ["Educational grants", "Performance measures", "Children with disabilities", "Eligibility criteria", "Education", "Aid for the disabled", "Elementary school students", "Special education", "Program evaluation", "Preschoolers", "Grant programs"], "type": "reports-testimonies", "url": "https://www.gao.gov/products/gao-02-394", "versions": [{"title": "Full Report (26 pages)", "url": "https://www.gao.gov/assets/gao-02-394.pdf"}, {"title": "Accessible Text", "url": "https://www.gao.gov/assets/a234093.html"}]}