{"gao_id": "GAO-21-158", "published": "2021-01-12T12:00:00Z", "released": "2021-01-12T07:00:00Z", "summary": "Protecting critical technologies\u2014such as those used in aeronautics and space systems\u2014is necessary for maintaining U.S. military superiority. Adversaries often try to steal or illegally export these technologies. Protecting them requires a collective effort from multiple federal agencies. DOD has begun compiling a list of acquisition programs, technologies, manufacturing capabilities, and research areas that are critical for preserving U.S. advantages. But it has not decided how...", "title": "DOD Critical Technologies: Plans for Communicating, Assessing, and Overseeing Protection Efforts Should Be Completed", "topics": ["Acquisition programs", "Federal agencies", "Military departments", "National security", "Export controls", "Defense acquisition programs", "National Defense", "Critical technologies", "Exports", "Emerging technologies", "Control systems"], "type": "reports-testimonies", "url": "https://www.gao.gov/products/gao-21-158", "versions": [{"title": "Highlights Page (1 page)", "url": "https://www.gao.gov/assets/gao-21-158-highlights.pdf"}, {"title": "Full Report (38 pages)", "url": "https://www.gao.gov/assets/gao-21-158.pdf"}, {"title": "Accessible PDF (48 pages)", "url": "https://www.gao.gov/assets/720/711740.pdf"}]}