{"gao_id": "GAO-02-645T", "published": "2002-04-26T13:00:00Z", "released": "2002-04-26T09:00:00Z", "summary": "", "title": "Veterans' Benefits: Despite Recent Improvements, Meeting Claims Processing Goals Will Be Challenging", "topics": ["Personnel management", "Performance measures", "National Defense", "Veterans", "Claims processing", "Veterans pensions", "Strategic planning", "Personnel recruiting", "Veterans disability compensation", "Pension claims", "Veterans benefits"], "type": "reports-testimonies", "url": "https://www.gao.gov/products/gao-02-645t", "versions": [{"title": "Full Report (15 pages)", "url": "https://www.gao.gov/assets/gao-02-645t.pdf"}, {"title": "Accessible Text", "url": "https://www.gao.gov/assets/a109296.html"}]}